LICENSE
MANIFEST.in
README.md
setup.cfg
setup.py
django_rest_generators/__init__.py
django_rest_generators/apps.py
django_rest_generators/generators.py
django_rest_generators/permissions.py
django_rest_generators.egg-info/PKG-INFO
django_rest_generators.egg-info/SOURCES.txt
django_rest_generators.egg-info/dependency_links.txt
django_rest_generators.egg-info/requires.txt
django_rest_generators.egg-info/top_level.txt
django_rest_generators/management/__init__.py
django_rest_generators/management/commands/__init__.py
django_rest_generators/management/commands/create_app.py
django_rest_generators/management/commands/create_model.py
django_rest_generators/management/commands/make_rest_model.py
django_rest_generators/steps/__init__.py
django_rest_generators/steps/authentication.py
django_rest_generators/steps/database.py
django_rest_generators/steps/http.py