Metadata-Version: 1.1
Name: django-rest-generators
Version: 0.1.6
Summary: Simple tool to add a bunch of commands related to django_rest_framework, django_guardian and behave
Home-page: https://github.com/Exanis/django-rest-generators
Author: Yann Piquet
Author-email: yann.piquet@epitech.eu
License: MIT
Download-URL: https://github.com/Exanis/django-rest-generators/archive/0.1.5.tar.gz
Keywords: testing,django,djangorestframework,behave
Platform: UNKNOWN
Classifier: Intended Audience :: Developers
Classifier: License :: OSI Approved :: MIT License
Classifier: Operating System :: OS Independent
Classifier: Programming Language :: Python
Classifier: Programming Language :: Python :: 2
Classifier: Programming Language :: Python :: 2.7
Classifier: Programming Language :: Python :: 3
Classifier: Programming Language :: Python :: 3.2
Classifier: Programming Language :: Python :: 3.3
Classifier: Programming Language :: Python :: 3.4
